LICENSE
MANIFEST.in
README.md
requirements.txt
setup.py
bin/ensurecvs
ensurecvs/__init__.py
ensurecvs/__main__.py
ensurecvs/arg_parser.py
ensurecvs.egg-info/PKG-INFO
ensurecvs.egg-info/SOURCES.txt
ensurecvs.egg-info/dependency_links.txt
ensurecvs.egg-info/requires.txt
ensurecvs.egg-info/top_level.txt
ensurecvs/classes/CSV_base.py
ensurecvs/classes/CVS.py
ensurecvs/classes/CVS_git.py
ensurecvs/classes/IssueFinder.py
ensurecvs/classes/__init__.py
ensurecvs/configs/__init__.py
ensurecvs/configs/extension_base.py
ensurecvs/configs/keywords_base.py